{
  "title": "Medieval Dynasty",
  "names": {
    "Unlimited Health": "Бесконечное здоровье",
    "Unlimited Stamina": "Бесконечная выносливость",
    "Never Hungry": "Без голода",
    "Never Thirsty": "Без жажды",
    "No Poison": "Без отравления",
    "Never Dirty": "Без загрязнения",
    "No Intoxication": "Без опьянения",
    "Unlimited Carry Weight": "Неограниченный переносимый вес",
    "+10 Skill Points": "+10 очков навыков",
    "+100 Skill Points": "+100 очков навыков",
    "Reset Skill Points": "Сбросить очки навыков",
    "Selected Item Amount": "Количество выбранного предмета",
    "Set Item Amount": "Задать количество предметов",
    "Amount to Add": "Количество для добавления",
    "Add Amount to Selected Item": "Добавить количество к выбранному предмету",
    "Repair Quick Slot Items": "Починить предметы в быстрых слотах",
    "Increase Max Health by 25%": "Увеличить макс. здоровье на 25%",
    "Max Health": "Макс. здоровье",
    "Increase Max Stamina by 25%": "Увеличить макс. выносливость на 25%",
    "Max Stamina": "Макс. выносливость",
    "Increase Cold Protection by 25%": "Увеличить защиту от холода на 25%",
    "Cold Protection": "Защита от холода",
    "Increase Heat Protection by 25%": "Увеличить защиту от жары на 25%",
    "Heat Protection": "Защита от жары",
    "Add 100 Building Tech Levels": "+100 уровней технологии строительства",
    "Building Tech Level": "Уровень технологии строительства",
    "Add 100 Crafting Tech Levels": "+100 уровней технологии ремесла",
    "Crafting Tech Level": "Уровень технологии ремесла",
    "Add 100 Farming Tech Levels": "+100 уровней технологии земледелия",
    "Farming Tech Level": "Уровень технологии земледелия",
    "Add 100 Survival Tech Levels": "+100 уровней технологии выживания",
    "Survival Tech Level": "Уровень технологии выживания",
    "Comfortable Low Temperature": "Комфортная низкая температура",
    "Comfortable High Temperature": "Комфортная высокая температура",
    "Age": "Возраст",
    "Overloaded Carry Weight": "Перегруз без штрафа",
    "One-Hit Kills": "Убийство с одного удара",
    "Free Crafting": "Бесплатный крафт",
    "Free Building": "Бесплатное строительство",
    "Instant Building": "Мгновенное строительство",
    "Time - Hours": "Время — часы",
    "Time - Minutes": "Время — минуты",
    "Skip Day": "Пропустить день",
    "Skip Season": "Пропустить сезон",
    "Game Speed Multiplier": "Множитель скорости игры",
    "Free Camera": "Свободная камера",
    "Fly Mode": "Режим полёта",
    "Fly Up": "Лететь вверх",
    "Fly Down": "Лететь вниз",
    "No Clip": "Проход сквозь стены",
    "Camera FOV": "Поле зрения камеры",
    "High Res Screenshot": "Скриншот в высоком разрешении",
    "Super Speed": "Суперскорость",
    "Player Speed Multiplier": "Множитель скорости игрока",
    "Low Gravity": "Низкая гравитация",
    "Gravity Scale": "Множитель гравитации",
    "Super Jump": "Суперпрыжок",
    "Jump Height Multiplier": "Множитель высоты прыжка",
    "Teleport to Vendor": "Телепорт к торговцу",
    "Teleport Height": "Высота телепорта",
    "Teleport to Waypoint": "Телепорт к маркеру"
  }
}
