{
  "title": "Palworld",
  "names": {
    "Infinite Player Health": "Бесконечное здоровье игрока",
    "Refill Health": "Восполнить здоровье",
    "Set Health Regeneration Rate": "Задать скорость регенерации здоровья",
    "Infinite Pal Health": "Бесконечное здоровье палов",
    "Infinite Stamina": "Бесконечная выносливость",
    "Infinite Satiety": "Бесконечная сытость",
    "Refill Satiety": "Восполнить сытость",
    "Set Player Satiety Decrease Rate": "Задать скорость убывания сытости",
    "Temperature Always Normal": "Температура всегда нормальная",
    "Set Stat Points": "Задать очки характеристик",
    "Set Technology Points": "Задать очки технологий",
    "Set Ancient Technology Points": "Задать очки древних технологий",
    "No Item Weight": "Предметы без веса",
    "Set Lifmunk Effigies": "Задать статуэтки лифмунка",
    "[Sel. Item] Set Amount": "[Выбр. предмет] задать количество",
    "Infinite Sanity": "Бесконечный рассудок",
    "Set Experience Multiplier": "Задать множитель опыта",
    "[Sel. Pal] Get Information": "[Выбр. пал] показать информацию",
    "[Sel. Pal] Set Level": "[Выбр. пал] задать уровень",
    "[Sel. Pal] Set Experience": "[Выбр. пал] задать опыт",
    "[Sel. Pal] Set Rank": "[Выбр. пал] задать ранг",
    "Infinite Weapon Durability": "Бесконечная прочность оружия",
    "[Overheat Rifle] No Heat": "[Винтовка с перегревом] без нагрева",
    "No Reload": "Без перезарядки",
    "Set Loot Drop Multiplier": "Задать множитель добычи",
    "[Player] Massive Work Speed": "[Игрок] огромная скорость работы",
    "[All] Massive Work Speed": "[Все] огромная скорость работы",
    "No Crafting Requirements": "Крафт без требований",
    "No Building Requirements": "Строительство без требований",
    "100% Capture Chance": "100% шанс поимки",
    "Capture Change Multiplier": "Множитель шанса поимки",
    "All Pals Are Rare": "Все палы редкие",
    "Rare Pal Probability Multiplier": "Множитель вероятности редких палов",
    "Instant Work Progress": "Мгновенный прогресс работы",
    "Extra Work Progress": "Доп. прогресс работы",
    "Infinite Torch Duration": "Бесконечный факел",
    "Infinite Base Structure Health": "Бесконечная прочность построек базы",
    "Everyone Can Be Captured": "Поймать можно любого",
    "Ignore Building Overlapping": "Игнорировать пересечение построек",
    "Stop Time": "Остановить время",
    "Set Daytime Speed Rate": "Задать скорость дня",
    "Set Nighttime Speed Rate": "Задать скорость ночи",
    "Instant Fishing": "Мгновенная рыбалка",
    "No Crime Reporting": "Преступления не замечают",
    "Fish Speed [%]": "Скорость рыбы [%]",
    "Pal Randomizer": "Рандомайзер палов",
    "Level Randomizer": "Рандомайзер уровней",
    "[Pal Level Randomizer] Set Min. Level": "[Рандомайзер уровней] мин. уровень",
    "[Pal Level Randomizer] Set Max Level": "[Рандомайзер уровней] макс. уровень",
    "Advance Time": "Время вперёд",
    "Rewind Time": "Время назад",
    "Instant Acceleration": "Мгновенное ускорение",
    "Set Walking Speed Multiplier": "Задать множитель скорости ходьбы",
    "Set Sprint Speed Multiplier": "Задать множитель скорости бега",
    "Set Jump Height Multiplier": "Задать множитель высоты прыжка"
  }
}
